pypeline_cli/__init__.py
pypeline_cli/_version.py
pypeline_cli/config.py
pypeline_cli/main.py
pypeline_cli/commands/__init__.py
pypeline_cli/commands/build.py
pypeline_cli/commands/create_pipeline.py
pypeline_cli/commands/create_processor.py
pypeline_cli/commands/init.py
pypeline_cli/commands/install.py
pypeline_cli/commands/sync_deps.py
pypeline_cli/core/__init__.py
pypeline_cli/core/create_project.py
pypeline_cli/core/managers/__init__.py
pypeline_cli/core/managers/dependencies_manager.py
pypeline_cli/core/managers/git_manager.py
pypeline_cli/core/managers/license_manager.py
pypeline_cli/core/managers/pipeline_manager.py
pypeline_cli/core/managers/processor_manager.py
pypeline_cli/core/managers/project_context.py
pypeline_cli/core/managers/scaffolding_manager.py
pypeline_cli/core/managers/toml_manager.py
pypeline_cli/templates/databricks/init/credentials.py.example.template
pypeline_cli/templates/databricks/init/databricks_utils.py.template
pypeline_cli/templates/databricks/init/decorators.py.template
pypeline_cli/templates/databricks/init/dependencies.py.template
pypeline_cli/templates/databricks/init/etl.py.template
pypeline_cli/templates/databricks/init/table_cache.py.template
pypeline_cli/templates/databricks/pipelines/README.md.template
pypeline_cli/templates/databricks/pipelines/config.py.template
pypeline_cli/templates/databricks/pipelines/processors_init.py.template
pypeline_cli/templates/databricks/pipelines/runner.py.template
pypeline_cli/templates/databricks/pipelines/tests_init.py.template
pypeline_cli/templates/databricks/processors/processor.py.template
pypeline_cli/templates/databricks/processors/test_processor.py.template
pypeline_cli/templates/licenses/apache_license_2_0.txt
pypeline_cli/templates/licenses/boost_software_license_1_0.txt
pypeline_cli/templates/licenses/bsd_2_clause_license.txt
pypeline_cli/templates/licenses/bsd_3_clause_license.txt
pypeline_cli/templates/licenses/creative_commons_zero_v1_0_universal.txt
pypeline_cli-0.8.1.dist-info/METADATA
pypeline_cli-0.8.1.dist-info/WHEEL
pypeline_cli-0.8.1.dist-info/entry_points.txt
pypeline_cli-0.8.1.dist-info/licenses/LICENSE
pypeline_cli-0.8.1.dist-info/RECORD
