Metadata-Version: 2.4
Name: pypeline-cli
Version: 0.8.1
Summary: A command-line tool that generates and maintains boilerplate code for data pipelines, allowing developers to focus on business logic while the CLI handles project structure, processor wiring, and orchestration.
Author-email: Daniel Brown <dannybrown540@live.com>
License-Expression: MIT
License-File: LICENSE
Keywords: cli,data,pipeline
Classifier: Development Status :: 3 - Alpha
Classifier: Environment :: Console
Classifier: Intended Audience :: Developers
Classifier: License :: OSI Approved :: MIT License
Classifier: Operating System :: OS Independent
Classifier: Programming Language :: Python :: 3
Classifier: Programming Language :: Python :: 3.12
Classifier: Programming Language :: Python :: 3.13
Classifier: Topic :: Software Development :: Code Generators
Classifier: Topic :: Software Development :: Libraries :: Python Modules
Requires-Python: >=3.12
Requires-Dist: click
Requires-Dist: tomli-w>=1.0.0
Provides-Extra: dev
Requires-Dist: build==1.3.0; extra == 'dev'
Requires-Dist: pre-commit==4.5.1; extra == 'dev'
Requires-Dist: pytest-asyncio==1.3.0; extra == 'dev'
Requires-Dist: pytest-cov==7.0.0; extra == 'dev'
Requires-Dist: pytest==9.0.2; extra == 'dev'
Requires-Dist: ruff==0.14.9; extra == 'dev'
Requires-Dist: twine==6.2.0; extra == 'dev'
